dot_analyzer/__init__.py
dot_analyzer/analyzer.py
dot_analyzer/dot_parser.py
dot_analyzer/graph_visualizer.py
dot_analyzer/tests/__init__.py
dot_analyzer/tests/test_analyze.py
dot_analyzer/tests/test_dot_parser.py
dot_analyzer/tests/fixtures/__init__.py
dot_analyzer/tests/fixtures/circle_graph.py
dot_analyzer/tests/fixtures/circled_nodes.py
dot_analyzer/tests/fixtures/nested_graph.py
dot_analyzer/tests/fixtures/simple_graph.py
dot_layered_transform-0.0.1.dist-info/licenses/LICENSE
dot_layered_transform-0.0.1.dist-info/METADATA
dot_layered_transform-0.0.1.dist-info/WHEEL
dot_layered_transform-0.0.1.dist-info/top_level.txt
dot_layered_transform-0.0.1.dist-info/RECORD
