Metadata-Version: 2.4
Name: dot-layered-transform
Version: 0.0.1
Summary: A Python tool for analyzing and visualizing architectural dependencies from DOT graphs.
Author-email: J4CK VVH173 <i78901234567890@gmail.com>
Project-URL: Homepage, https://github.com/your-github-username/dot-layered-transform
Project-URL: Bug Tracker, https://github.com/your-github-username/dot-layered-transform/issues
Keywords: dot,graph,architecture,dependencies,visualization,analyzer
Classifier: Programming Language :: Python :: 3
Classifier: License :: OSI Approved :: MIT License
Classifier: Operating System :: OS Independent
Classifier: Development Status :: 3 - Alpha
Classifier: Intended Audience :: Developers
Classifier: Topic :: Software Development :: Quality Assurance
Classifier: Topic :: Software Development :: Libraries :: Python Modules
Classifier: Topic :: Scientific/Engineering :: Visualization
Requires-Python: >=3.10
License-File: LICENSE
Dynamic: license-file
